py_exporter/__init__.py
py_exporter/_enums.py
py_exporter/_main.py
py_exporter/_utils.py
py_package_exporter-0.0.4.dist-info/licenses/LICENSE
py_package_exporter-0.0.4.dist-info/METADATA
py_package_exporter-0.0.4.dist-info/WHEEL
py_package_exporter-0.0.4.dist-info/top_level.txt
py_package_exporter-0.0.4.dist-info/RECORD
