Metadata-Version: 2.4
Name: py_package_exporter
Version: 0.0.4
Summary: A package to help building your python apps with PyInstaller
Home-page: https://github.com/RadoslawDrab/PyExporter
Author: Radosław Drab
License: MIT License
Keywords: exporter,packages,pyinstaller,installer
License-File: LICENSE
Dynamic: author
Dynamic: description
Dynamic: description-content-type
Dynamic: home-page
Dynamic: keywords
Dynamic: license
Dynamic: license-file
Dynamic: summary
